meritrank_python/__init__.py
meritrank_python/lazy.py
meritrank_python/rank.py
meritrank_python-0.2.10.dist-info/LICENSE
meritrank_python-0.2.10.dist-info/WHEEL
meritrank_python-0.2.10.dist-info/METADATA
meritrank_python-0.2.10.dist-info/RECORD
