Metadata-Version: 2.1
Name: meritrank-python
Version: 0.2.10
Summary: MeritRank decentralized, sybil-resistant, personalized ranking algorithm library
Home-page: https://github.com/ichorid/meritrank-python
License: GPLv2
Author: V.G. Bulavintsev
Author-email: golem.md@gmail.com
Requires-Python: >=3.10
Classifier: License :: Other/Proprietary License
Classifier: Programming Language :: Python :: 3
Classifier: Programming Language :: Python :: 3.10
Classifier: Programming Language :: Python :: 3.11
Requires-Dist: networkx (>=2.8.8)
Project-URL: Repository, https://github.com/ichorid/meritrank-python
